setup.py
skiff/Action.py
skiff/Domain.py
skiff/Droplet.py
skiff/Image.py
skiff/Kernel.py
skiff/Key.py
skiff/Network.py
skiff/Region.py
skiff/Size.py
skiff/__init__.py
skiff/utils.py
skiff.egg-info/PKG-INFO
skiff.egg-info/SOURCES.txt
skiff.egg-info/dependency_links.txt
skiff.egg-info/entry_points.txt
skiff.egg-info/requires.txt
skiff.egg-info/top_level.txt