Metadata-Version: 1.1
Name: skiff
Version: 0.9.5
Summary: Python library for DigitalOcean's v2 API
Home-page: http://github.com/Shrugs/skiff
Author: Matt Condon
Author-email: m@cond.in
License: MIT
Keywords: digitalocean api library v2
Platform: UNKNOWN
Classifier: Development Status :: 4 - Beta
Classifier: Intended Audience :: Developers
Classifier: License :: OSI Approved :: MIT License
Classifier: Natural Language :: English
Classifier: Operating System :: Unix
Classifier: Programming Language :: Python :: 2.6
Classifier: Programming Language :: Python :: 2.7
Classifier: Programming Language :: Python :: Implementation :: PyPy
Classifier: Operating System :: OS Independent
